gig/__init__.py
gig/gig.py
gig/models.py
gig_python-0.0.1.dist-info/LICENSE
gig_python-0.0.1.dist-info/METADATA
gig_python-0.0.1.dist-info/WHEEL
gig_python-0.0.1.dist-info/top_level.txt
gig_python-0.0.1.dist-info/RECORD
